{
  "id": "82e392fe-a06d-4044-baec-8eabd7633094",
  "prevId": "71aba641-d4b3-4bda-a405-9519fc093324",
  "version": "5",
  "dialect": "pg",
  "tables": {
    "comment": {
      "name": "comment",
      "schema": "",
      "columns": {
        "id": {
          "name": "id",
          "type": "uuid",
          "primaryKey": true,
          "notNull": true,
          "default": "gen_random_uuid()"
        },
        "commenter_id": {
          "name": "commenter_id",
          "type": "uuid",
          "primaryKey": false,
          "notNull": true
        },
        "file_id": {
          "name": "file_id",
          "type": "uuid",
          "primaryKey": false,
          "notNull": true
        },
        "text": {
          "name": "text",
          "type": "text",
          "primaryKey": false,
          "notNull": true
        }
      },
      "indexes": {},
      "foreignKeys": {
        "comment_commenter_id_user_id_fk": {
          "name": "comment_commenter_id_user_id_fk",
          "tableFrom": "comment",
          "tableTo": "user",
          "columnsFrom": [
            "commenter_id"
          ],
          "columnsTo": [
            "id"
          ],
          "onDelete": "no action",
          "onUpdate": "no action"
        },
        "comment_file_id_file_id_fk": {
          "name": "comment_file_id_file_id_fk",
          "tableFrom": "comment",
          "tableTo": "file",
          "columnsFrom": [
            "file_id"
          ],
          "columnsTo": [
            "id"
          ],
          "onDelete": "no action",
          "onUpdate": "no action"
        }
      },
      "compositePrimaryKeys": {},
      "uniqueConstraints": {}
    },
    "file": {
      "name": "file",
      "schema": "",
      "columns": {
        "id": {
          "name": "id",
          "type": "uuid",
          "primaryKey": true,
          "notNull": true,
          "default": "gen_random_uuid()"
        },
        "name": {
          "name": "name",
          "type": "text",
          "primaryKey": false,
          "notNull": true
        }
      },
      "indexes": {},
      "foreignKeys": {},
      "compositePrimaryKeys": {},
      "uniqueConstraints": {}
    },
    "tag": {
      "name": "tag",
      "schema": "",
      "columns": {
        "id": {
          "name": "id",
          "type": "uuid",
          "primaryKey": true,
          "notNull": true,
          "default": "gen_random_uuid()"
        },
        "name": {
          "name": "name",
          "type": "text",
          "primaryKey": false,
          "notNull": true
        }
      },
      "indexes": {},
      "foreignKeys": {},
      "compositePrimaryKeys": {},
      "uniqueConstraints": {}
    },
    "tags_pivot": {
      "name": "tags_pivot",
      "schema": "",
      "columns": {
        "id": {
          "name": "id",
          "type": "uuid",
          "primaryKey": false,
          "notNull": true,
          "default": "gen_random_uuid()"
        },
        "file_id": {
          "name": "file_id",
          "type": "uuid",
          "primaryKey": false,
          "notNull": true
        },
        "tag_id": {
          "name": "tag_id",
          "type": "uuid",
          "primaryKey": false,
          "notNull": true
        }
      },
      "indexes": {},
      "foreignKeys": {
        "tags_pivot_file_id_file_id_fk": {
          "name": "tags_pivot_file_id_file_id_fk",
          "tableFrom": "tags_pivot",
          "tableTo": "file",
          "columnsFrom": [
            "file_id"
          ],
          "columnsTo": [
            "id"
          ],
          "onDelete": "no action",
          "onUpdate": "no action"
        },
        "tags_pivot_tag_id_tag_id_fk": {
          "name": "tags_pivot_tag_id_tag_id_fk",
          "tableFrom": "tags_pivot",
          "tableTo": "tag",
          "columnsFrom": [
            "tag_id"
          ],
          "columnsTo": [
            "id"
          ],
          "onDelete": "no action",
          "onUpdate": "no action"
        }
      },
      "compositePrimaryKeys": {
        "tags_pivot_file_id_tag_id_pk": {
          "name": "tags_pivot_file_id_tag_id_pk",
          "columns": [
            "file_id",
            "tag_id"
          ]
        }
      },
      "uniqueConstraints": {}
    },
    "user": {
      "name": "user",
      "schema": "",
      "columns": {
        "id": {
          "name": "id",
          "type": "uuid",
          "primaryKey": true,
          "notNull": true,
          "default": "gen_random_uuid()"
        },
        "name": {
          "name": "name",
          "type": "text",
          "primaryKey": false,
          "notNull": true
        }
      },
      "indexes": {},
      "foreignKeys": {},
      "compositePrimaryKeys": {},
      "uniqueConstraints": {}
    }
  },
  "enums": {},
  "schemas": {},
  "_meta": {
    "schemas": {},
    "tables": {},
    "columns": {}
  }
}